Dotnet_Leetcode_Template/Dotnet_Leetcode_Template_Script.py
dotnet_leetcode_template-1.0.0.dist-info/LICENSE
dotnet_leetcode_template-1.0.0.dist-info/METADATA
dotnet_leetcode_template-1.0.0.dist-info/WHEEL
dotnet_leetcode_template-1.0.0.dist-info/entry_points.txt
dotnet_leetcode_template-1.0.0.dist-info/top_level.txt
dotnet_leetcode_template-1.0.0.dist-info/RECORD
