Metadata-Version: 2.1
Name: dotnet-leetcode-template
Version: 1.0.0
Summary: Automation script to create a new LeetCode problem solutions in C#
Home-page: https://github.com/SasankPeetha8/Dotnet-Leetcode-Template
Author: Sasank Peetha
Author-email: sasank85@outlook.com
Project-URL: Dotnet Dependency, https://dotnet.microsoft.com/
Classifier: Development Status :: 5 - Production/Stable
Classifier: Intended Audience :: Developers
Classifier: License :: OSI Approved :: GNU General Public License v3 (GPLv3)
Classifier: Programming Language :: Python :: 3.10
Classifier: Operating System :: OS Independent
Classifier: Topic :: Software Development :: Build Tools
Requires-Python: >=3.7
License-File: LICENSE
